tipi/__init__.py
tipi/abstractions.py
tipi/cli.py
tipi/decorators.py
tipi/errors.py
tipi/helpers.py
tipi/paths.py
tipi/template_manager.py
tipi/abstractions/__init__.py
tipi/abstractions/config.py
tipi/abstractions/controller.py
tipi/abstractions/permanence.py
tipi/abstractions/process.py
tipi/core/__init__.py
tipi/core/builder.py
tipi/core/config.py
tipi/core/controller.py
tipi/core/executor.py
tipi/core/permanences.py
tipi/core/processes.py
tipi/core/runner.py
tipi/core/utils.py
tipi/pipelines/__init__.py
pytorchimagepipeline-0.0.5.dist-info/METADATA
pytorchimagepipeline-0.0.5.dist-info/WHEEL
pytorchimagepipeline-0.0.5.dist-info/entry_points.txt
pytorchimagepipeline-0.0.5.dist-info/licenses/LICENSE
pytorchimagepipeline-0.0.5.dist-info/RECORD
