Metadata-Version: 2.4
Name: PytorchImagePipeline
Version: 0.0.5
Summary: This is a repository for creating and running Tipi Pipelines.
Project-URL: Homepage, https://tensorimgpipeline.github.io/TensorImgPipeline/
Project-URL: Repository, https://github.com/tensorimgpipeline/TensorImgPipeline
Project-URL: Documentation, https://tensorimgpipeline.github.io/TensorImgPipeline/
Author-email: Matti Kaupenjohann <matti.kaupenjohann@fh-dortmund.de>
License-File: LICENSE
Keywords: python
Classifier: Intended Audience :: Developers
Classifier: Programming Language :: Python
Classifier: Programming Language :: Python :: 3
Classifier: Programming Language :: Python :: 3.11
Classifier: Programming Language :: Python :: 3.12
Classifier: Programming Language :: Python :: 3.13
Classifier: Topic :: Software Development :: Libraries :: Python Modules
Requires-Python: <4.0,>=3.11
Requires-Dist: defusedxml>=0.7.1
Requires-Dist: jinja2>=3.1.0
Requires-Dist: matplotlib>=3.9.4
Requires-Dist: numpy>=2.0.2
Requires-Dist: opencv-python>=4.11.0.86
Requires-Dist: pydantic>=2.0.0
Requires-Dist: rich>=13.9.4
Requires-Dist: torch>=2.6.0
Requires-Dist: torchvision>=0.21.0
Requires-Dist: tqdm>=4.67.1
Requires-Dist: typer>=0.15.1
Requires-Dist: types-defusedxml>=0.7.0.20240218
Requires-Dist: wandb>=0.19.6
